archivant/__init__.py
archivant/archivant.py
archivant/exceptions.py
cli/__init__.py
cli/agherant.py
cli/custom_types.py
cli/libreant.py
cli/libreant_db.py
cli/libreant_users.py
conf/__init__.py
conf/config_utils.py
conf/defaults.py
libreant-0.6.dist-info/DESCRIPTION.rst
libreant-0.6.dist-info/METADATA
libreant-0.6.dist-info/RECORD
libreant-0.6.dist-info/WHEEL
libreant-0.6.dist-info/entry_points.txt
libreant-0.6.dist-info/metadata.json
libreant-0.6.dist-info/top_level.txt
libreantdb/__init__.py
libreantdb/api.py
libreantdb/exceptions.py
libreantdb/migration.py
presets/__init__.py
presets/presetManager.py
users/__init__.py
users/api.py
users/models.py
utils/__init__.py
utils/es.py
utils/loggers.py
webant/__init__.py
webant/agherant.py
webant/agherant_standalone.py
webant/auth.py
webant/constants.py
webant/util.py
webant/webant.py
webant/webserver_utils.py
webant/api/__init__.py
webant/api/archivant_api.py
webant/api/blueprint_api.py
webant/api/users_api.py
webant/api/util.py
webant/static/edit.css
webant/static/item_list.css
webant/static/search.css
webant/static/js/action-toolbar.js
webant/static/js/add-volume.js
webant/static/js/bootstrap-filestyle.min.js
webant/static/js/edit-volume.js
webant/templates/add.html
webant/templates/details.html
webant/templates/edit-volume.html
webant/templates/error.html
webant/templates/index.html
webant/templates/login.html
webant/templates/navbar.html
webant/templates/opens.xml
webant/templates/opens_desc.xml
webant/templates/os_opens.xml
webant/templates/os_search.html
webant/templates/pagination.html
webant/templates/recents.html
webant/templates/search.html
webant/templates/searchbar.html
webant/translations/en/LC_MESSAGES/messages.mo
webant/translations/en/LC_MESSAGES/messages.po
webant/translations/it/LC_MESSAGES/messages.mo
webant/translations/it/LC_MESSAGES/messages.po
webant/translations/sq/LC_MESSAGES/messages.mo
webant/translations/sq/LC_MESSAGES/messages.po
