Metadata-Version: 2.0
Name: libreant
Version: 0.6
Summary: {e,}book archive focused on small grass root archives, distributed search, low assumptions
Home-page: https://github.com/insomnia-lab/libreant
Author: insomnialab
Author-email: insomnialab@hacari.org
License: AGPL
Platform: UNKNOWN
Classifier: Framework :: Flask
Classifier: License :: OSI Approved :: GNU Affero General Public License v3
Classifier: Operating System :: POSIX :: Linux
Classifier: Programming Language :: Python :: 2
Classifier: Development Status :: 4 - Beta
Requires-Dist: gevent (<1.3,>=1.0.1)
Requires-Dist: elasticsearch (<7.0.0,>=6.0.0)
Requires-Dist: flask-bootstrap (<4)
Requires-Dist: Flask-Babel
Requires-Dist: Flask-Authbone (>=0.2.2)
Requires-Dist: Flask (<0.13)
Requires-Dist: opensearch
Requires-Dist: Fsdb (<1.3,>=0.3.3)
Requires-Dist: click
Requires-Dist: peewee (!=2.8.2,<2.11)
Requires-Dist: passlib (<1.8,>=1.6)
